dphonebook/__init__.py
dphonebook/cli.py
dphonebook/disposable-phonebook.yml
dphonebook/phonebook.py
dphonebook/lib/__init__.py
dphonebook/lib/numberprovider.py
dphonebook/lib/phonenumber.py
dphonebook/lib/progress.py
dphonebook/lib/session.py
dphonebook/lib/providers/__init__.py
dphonebook/lib/providers/dummy_example_com.py
dphonebook/lib/providers/receive_sms_co.py
dphonebook/lib/providers/receive_sms_free_cc.py
dphonebook/lib/providers/receive_sms_online_info.py
dphonebook/lib/providers/receive_sms_org.py
dphonebook/lib/providers/receive_smss.py
dphonebook/lib/providers/sms_online_co.py
dphonebook/lib/writer/__init__.py
dphonebook/lib/writer/json_writer.py
dphonebook/lib/writer/result_writer.py
dphonebook/lib/writer/stdout_writer.py
dphonebook/lib/writer/webhook_writer.py
dphonebook/vendor/user-agents/LICENSE
dphonebook/vendor/user-agents/user-agents.json.gz
disposable_phonebook-0.4.1.dist-info/LICENSE
disposable_phonebook-0.4.1.dist-info/METADATA
disposable_phonebook-0.4.1.dist-info/WHEEL
disposable_phonebook-0.4.1.dist-info/entry_points.txt
disposable_phonebook-0.4.1.dist-info/top_level.txt
disposable_phonebook-0.4.1.dist-info/RECORD
