Metadata-Version: 2.1
Name: disposable-phonebook
Version: 0.4.1
Summary: Scraper for disposable phone number services
Home-page: https://github.com/anroots/disposable-phonebook
Author: Ando Roots
Author-email: ando@sqroot.eu
License: Apache 2.0
Project-URL: Documentation, https://anroots.github.io/disposable-phonebook/
Project-URL: Source Code, https://github.com/anroots/disposable-phonebook
Platform: UNKNOWN
Classifier: Programming Language :: Python :: 3.10
Classifier: Programming Language :: Python :: 3 :: Only
Classifier: Programming Language :: Python :: 3
Classifier: Development Status :: 2 - Pre-Alpha
Classifier: Environment :: Console
Classifier: Intended Audience :: Developers
Classifier: License :: OSI Approved :: Apache Software License
Classifier: Operating System :: OS Independent
Classifier: Topic :: Communications :: Telephony
License-File: LICENSE
Requires-Dist: requests
Requires-Dist: click
Requires-Dist: setuptools
Requires-Dist: beautifulsoup4
Requires-Dist: phonenumbers
Requires-Dist: pyyaml
Requires-Dist: tqdm
